juridecomposer/__init__.py
juridecomposer/dict_to_dataframe.py
juridecomposer/example.xml
juridecomposer/juridecomposer.py
juridecomposer/wetten_xml_to_dict.py
juridecomposer-0.4.11.dist-info/entry_points.txt
juridecomposer-0.4.11.dist-info/LICENSE
juridecomposer-0.4.11.dist-info/WHEEL
juridecomposer-0.4.11.dist-info/METADATA
juridecomposer-0.4.11.dist-info/RECORD
