Metadata-Version: 2.1
Name: juridecomposer
Version: 0.4.11
Summary: 
Home-page: https://gitlab.com/calculemus-flint/flintfillers/flintfiller-rlb
License: Apache-2.0
Author: Roos Bakker
Author-email: roos.bakker@tno.nl
Requires-Python: >=3.6.1,<3.7
Classifier: License :: OSI Approved :: Apache Software License
Classifier: Programming Language :: Python :: 3
Requires-Dist: pandas (>=1.0.5,<2.0.0)
Requires-Dist: xmltodict (>=0.12.0,<0.13.0)
Project-URL: Repository, https://gitlab.com/calculemus-flint/flintfillers/flintfiller-rlb
